{
    "穀類":{
        "オートミール":"オートミール",
        "おーとみーる":"オートミール",
        "おおむぎ":"おおむぎ",
        "大麦":"おおむぎ",
        "オオムギ":"おおむぎ",
        "はくりきこ":"薄力粉",
        "薄力粉":"薄力粉",
        "こむぎこ":"薄力粉",
        "コムギコ":"薄力粉",
        "小麦粉":"薄力粉",
        "きょうりきこ":"強力粉",
        "強力粉":"強力粉",
        "ぱん":"パン",
        "パン":"パン",
        "うどん":"うどん",
        "饂飩":"うどん",
        "ウドン":"うどん",
        "そうめん":"そうめん",
        "ソウメン":"そうめん",
        "素麺":"そうめん",
        "ちゅうかめん":"中華めん",
        "中華麺":"中華めん",
        "中華めん":"中華めん",
        "マカロニ":"マカロニ・スパゲッティ",
        "まかろに":"マカロニ・スパゲッティ",
        "すぱげってぃ":"マカロニ・スパゲッティ",
        "スパゲッティ":"マカロニ・スパゲッティ",
        "パスタ":"マカロニ・スパゲッティ",
        "ぱすた":"マカロニ・スパゲッティ",
        "ふ":"ふ",
        "フ":"ふ",
        "麩":"ふ",
        "ぎょうざのかわ":"餃子の皮",
        "餃子の皮":"餃子の皮",
        "ぱんこ":"パン粉",
        "パン粉":"パン粉",
        "こめ":"米",
        "コメ":"米",
        "米":"米",
        "きりたんぽ":"きりたんぽ",
        "切りたんぽ":"きりたんぽ",
        "じょうしんこ":"上新粉",
        "上新粉":"上新粉",
        "ビーフン":"ビーフン",
        "びーふん":"ビーフン",
        "こめこうじ":"米麹",
        "米麹":"米麹",
        "もち":"もち",
        "餅":"もち",
        "モチ":"もち",
        "しらたまこ":"白玉粉",
        "白玉粉":"白玉粉",
        "そばこ":"そば粉",
        "そば粉":"そば粉",
        "蕎麦粉":"そば粉",
        "そば":"そば",
        "蕎麦":"そば",
        "ソバ":"そば",
        "とうもろこし":"とうもろこし",
        "トウモロコシ":"とうもろこし",
        "玉蜀黍":"とうもろこし",
        "こーんふれーく":"コーンフレーク",
        "コーンフレーク":"コーンフレーク",
        "はとむぎ":"はとむぎ",
        "ハトムギ":"はとむぎ",
        "鳩麦":"はとむぎ",
        "こめこめん":"米粉めん",
        "米粉めん":"米粉めん",
        "米粉麺":"米粉めん",
        "らいすぺーぱー":"ライスペーパー",
        "ライスペーパー":"ライスペーパー",
        "かやきせんべい":"かやきせんべい",
        "はるまきのかわ":"春巻きの皮",
        "春巻きの皮":"春巻きの皮"
    },
    "いも及びデンプン類":{
        "こんにゃく":"こんにゃく",
        "コンニャク":"こんにゃく",
        "蒟蒻":"こんにゃく",
        "しらたき":"しらたき",
        "白滝":"しらたき",
        "シラタキ":"しらたき",
        "さつまいも":"さつまいも",
        "サツマイモ":"さつまいも",
        "薩摩芋":"さつまいも",
        "さといも":"さといも",
        "里芋":"さといも",
        "じゃがいも":"じゃがいも",
        "馬鈴薯":"じゃがいも",
        "ジャガイモ":"じゃがいも",
        "フライドポテト":"フライドポテト",
        "ふらいどぽてと":"フライドポテト",
        "ながいも":"ながいも",
        "ナガイモ":"ながいも",
        "長芋":"ながいも",
        "じねんじょ":"じねんじょ",
        "自然薯":"じねんじょ",
        "でんこ":"でんこ",
        "くずきり":"くずきり",
        "葛切り":"くずきり",
        "はるさめ":"はるさめ",
        "春雨":"はるさめ",
        "セレベス":"セレベス",
        "せれべす":"セレベス",
        "たこのいも":"たこのいも"
    },
    "豆類":{
        "あずき":"あずき",
        "小豆":"あずき",
        "アズキ":"あずき",
        "いんげんまめ":"いんげんまめ",
        "インゲン豆":"いんげんまめ",
        "ささげ":"ささげ",
        "だいず":"だいず",
        "大豆":"だいず",
        "きなこ":"きな粉",
        "きな粉":"きな粉",
        "木綿豆腐":"木綿豆腐",
        "もめんとうふ":"木綿豆腐",
        "きぬごしとうふ":"絹ごし豆腐",
        "おきなわとうふ":"沖縄豆腐",
        "沖縄豆腐":"沖縄豆腐",
        "やきどうふ":"焼き豆腐",
        "焼き豆腐":"焼き豆腐",
        "なまあげ":"生揚げ",
        "生揚げ":"生揚げ",
        "あぶらあげ":"油揚げ",
        "油揚げ":"油揚げ",
        "がんもどき":"がんもどき",
        "飛龍頭":"がんもどき",
        "凍り豆腐":"凍り豆腐",
        "こおりどうふ":"凍り豆腐",
        "なっとう":"納豆",
        "納豆":"納豆",
        "ひきわりなっとう":"挽きわり納豆",
        "挽きわり納豆":"挽きわり納豆",
        "挽き割り納豆":"挽きわり納豆",
        "おから":"おから",
        "とうにゅう":"豆乳",
        "豆乳":"豆乳",
        "湯葉":"湯葉",
        "ゆば":"湯葉",
        "ひよこまめ":"ひよこ豆",
        "雛豆":"ひよこ豆",
        "れんずまめ":"レンズ豆",
        "レンズ豆":"レンズ豆"
    },
    "種実類":{
        "アーモンド":"アーモンド",
        "あーもんど":"アーモンド",
        "カシューナッツ":"カシューナッツ",
        "かしゅーなっつ":"カシューナッツ",
        "ぎんなん":"ぎんなん",
        "銀杏":"ぎんなん",
        "くり":"くり",
        "栗":"くり",
        "くるみ":"くるみ",
        "胡桃":"くるみ",
        "けし":"けし",
        "ケシ":"けし",
        "芥子":"けし",
        "ごま":"ごま",
        "胡麻":"ごま",
        "ゴマ":"ごま",
        "まつ":"まつ",
        "松":"まつ",
        "らっかせい":"らっかせい",
        "落花生":"らっかせい",
        "バターピーナッツ":"バターピーナッツ",
        "ピーナッツバター":"ピーナッツバター"
    },
    "野菜類":{
        "あさつき":"あさつき",
        "浅葱":"あさつき",
        "あすぱらがす":"アスパラガス",
        "アスパラガス":"アスパラガス",
        "さやいんげん":"さやいんげん",
        "うど":"うど",
        "ウド":"うど",
        "えだまめ":"えだまめ",
        "枝豆":"えだまめ",
        "えんだいぶ":"エンダイブ",
        "とうみょう":"とうみょう",
        "豆苗":"とうみょう",
        "さやえんどう":"さやえんどう",
        "サヤエンドウ":"さやえんどう",
        "スナップエンドウ":"スナップえんどう",
        "スナップえんどう":"スナップえんどう",
        "グリンピース":"グリンピース",
        "ぐりんぴーす":"グリンピース",
        "おかひじき":"おかひじき",
        "オクラ":"オクラ",
        "おくら":"オクラ",
        "かぶ":"かぶ",
        "蕪":"かぶ",
        "カブ":"かぶ",
        "かぼちゃ":"かぼちゃ",
        "カボチャ":"かぼちゃ",
        "南瓜":"かぼちゃ",
        "カリフラワー":"カリフラワー",
        "かりふらわー":"カリフラワー",
        "かんぴょう":"かんぴょう",
        "干瓢":"かんぴょう",
        "きく":"きく",
        "菊":"きく",
        "キャベツ":"キャベツ",
        "きゃべつ":"キャベツ",
        "きゅうり":"きゅうり",
        "胡瓜":"きゅうり",
        "ピクルス":"ピクルス",
        "ぴくるす":"ピクルス",
        "みずな":"みずな",
        "水菜":"みずな",
        "クレソン":"クレソン",
        "くれそん":"クレソン",
        "くわい":"くわい",
        "慈姑":"くわい",
        "こごみ":"こごみ",
        "ごぼう":"ごぼう",
        "牛蒡":"ごぼう",
        "ゴボウ":"ごぼう",
        "こまつな":"こまつな",
        "小松菜":"こまつな",
        "ザーサイ":"ザーサイ",
        "ざーさい":"ザーサイ",
        "搾菜":"ザーサイ",
        "ししとう":"ししとう",
        "獅子唐":"ししとう",
        "紫蘇":"しそ",
        "しそ":"しそ",
        "春菊":"しゅんぎく",
        "しゅんぎく":"しゅんぎく",
        "じゅんさい":"じゅんさい",
        "ジュンサイ":"じゅんさい",
        "しょうが":"しょうが",
        "生姜":"しょうが",
        "しょうが　つけもの":"しょうが　漬物",
        "生姜　漬物":"しょうが　漬物",
        "しろうり":"しろうり",
        "白瓜":"しろうり",
        "シロウリ":"しろうり",
        "ずいき":"ずいき",
        "芋茎":"ずいき",
        "ズッキーニ":"ズッキーニ",
        "せり":"せり",
        "芹":"せり",
        "セロリ":"セロリ",
        "せろり":"セロリ",
        "ぜんまい":"ぜんまい",
        "ゼンマイ":"ぜんまい",
        "薇":"ぜんまい",
        "そらまめ":"そらまめ",
        "たあさい":"タアサイ",
        "タアサイ":"タアサイ",
        "かいわれだいこん":"かいわれ大根",
        "貝割れ大根":" かいわれ大根",
        "カイワレダイコン":"かいわれ大根",
        "だいこん":"大根",
        "ダイコン":"大根",
        "大根":"大根",
        "切り干し大根":"切り干し大根",
        "きりぼしだいこん":"切り干し大根",
        "キリボシダイコン":"切り干し大根",
        "たくあん":"たくあん",
        "たかな":"たかな",
        "タカナ":"たかな",
        "高菜":"たかな",
        "たけのこ":"たけのこ",
        "筍":"たけのこ",
        "めんま":"めんま",
        "メンマ":"めんま",
        "たまねぎ":"たまねぎ",
        "玉ねぎ":"たまねぎ",
        "玉葱":"たまねぎ",
        "たらのめ":"たらのめ",
        "タラノメ":"たらのめ",
        "チコリ":"チコリ",
        "ちこり":"チコリ",
        "青梗菜":"ちんげんさい",
        "ちんげんさい":"ちんげんさい",
        "チンゲンサイ":"ちんげんさい",
        "つるむらさき":"つるむらさき",
        "蔓紫":"つるむらさき",
        "ツルムラサキ":"つるむらさき",
        "とうがらし":"とうがらし",
        "唐辛子":"とうがらし",
        "トウガラシ":"とうがらし",
        "とうがん":"とうがん",
        "冬瓜":"とうがん",
        "トウガン":"とうがん",
        "スイートコーン":"スイートコーン",
        "すいーとこーん":"スイートコーン",
        "やんぐこーん":"ヤングコーン",
        "ヤングコーン":"ヤングコーン",
        "トマト":"トマト",
        "とまと":"トマト",
        "みにとまと":"ミニトマト",
        "ミニトマト":"ミニトマト",
        "ホールトマト缶":"ホールトマト缶",
        "ほーるとまとかん":"ホールトマト缶",
        "トマトジュース":"トマトジュース",
        "とまとじゅーす":"トマトジュース",
        "とれびす":"トレビス",
        "トレビス":"トレビス",
        "なす":"なす",
        "ナス":"なす",
        "茄子":"なす",
        "なす　漬物":"なす　漬物",
        "ナス　漬物":"なす　漬物",
        "茄子　漬物":"なす　漬物",
        "なばな":"なばな",
        "菜花":"なばな",
        "ナバナ":"なばな",
        "ニガウリ":"にがうり",
        "にがうり":"にがうり",
        "苦瓜":"にがうり",
        "にら":"にら",
        "ニラ":"にら",
        "韮":"にら",
        "にんじん":"にんじん",
        "ニンジン":"にんじん",
        "人参":"にんじん",
        "きんとき":"きんとき",
        "金時":"きんとき",
        "キントキ":"きんとき",
        "にんにく":"にんにく",
        "ニンニク":"にんにく",
        "大蒜":"にんにく",
        "ねぎ":"ねぎ",
        "野沢菜":"野沢菜",
        "のざわな":"野沢菜",
        "はくさい":"はくさい",
        "白菜":"はくさい",
        "ハクサイ":"はくさい",
        "はくさい　漬物":"はくさい　漬物",
        "はくさい　つけもの":"はくさい　漬物",
        "はくさい　漬け物":"はくさい　漬物",
        "白菜　漬物":"はくさい　漬物",
        "キムチ":"キムチ",
        "きむち":"キムチ",
        "バジル":"バジル",
        "ばじる":"バジル",
        "ぱせり":"パセリ",
        "パセリ":"パセリ",
        "二十日大根":"二十日大根",
        "ハツカダイコン":"二十日大根",
        "はつかだいこん":"二十日大根",
        "ピーマン":"ピーマン",
        "ぴーまん":"ピーマン",
        "ふき":"ふき",
        "蕗":"ふき",
        "フキ":"ふき",
        "ふきのとう":"ふきのとう",
        "蕗の薹":"ふきのとう",
        "ブロッコリー":"ブロッコリー",
        "ぶろっこりー":"ブロッコリー",
        "へちま":"へちま",
        "糸瓜":"へちま",
        "ほうれんそう":"ほうれんそう",
        "ホウレンソウ":"ほうれんそう",
        "みつば":"みつば",
        "ミツバ":"みつば",
        "三つ葉":"みつば",
        "みょうが":"みょうが",
        "茗荷":"みょうが",
        "ミョウガ":"みょうが",
        "めきゃべつ":"めキャベツ",
        "メキャベツ":"めキャベツ",
        "芽キャベツ":"めキャベツ",
        "めたで":"めたで",
        "もやし":"もやし",
        "モヤシ":"もやし",
        "もろへいや":"モロヘイヤ",
        "モロヘイヤ":"モロヘイヤ",
        "ゆりね":"ゆりね",
        "ユリネ":"ゆりね",
        "ようさい":"ようさい",
        "葉菜":"ようさい",
        "らっきょう":"らっきょう",
        "辣韮":"らっきょう",
        "エシャレット":"エシャレット",
        "えしゃれっと":"エシャレット",
        "れたす":"レタス",
        "レタス":"レタス",
        "れんこん":"れんこん",
        "蓮根":"れんこん",
        "レンコン":"れんこん",
        "ルッコラ":"ルッコラ",
        "るっこら":"ルッコラ",
        "わけぎ":"わけぎ",
        "ワケギ":"わけぎ",
        "分葱":"わけぎ",
        "わさび":"わさび",
        "ワサビ":"わさび",
        "山葵":"わさび",
        "わらび":"わらび",
        "ワラビ":"わらび",
        "どらいとまと":"ドライトマト",
        "ドライトマト":"ドライトマト",
        "みっくすべじたぶる":"ミックスベジタブル",
        "ミックスベジタブル":"ミックスベジタブル",
        "コリアンダー":"コリアンダー",
        "こりあんだー":"コリアンダー",
        "すいぜんじな":"すいぜんじな",
        "スイゼンジナ":"すいぜんじな",
        "水前寺菜":"すいぜんじな",
        "いぶりがっこ":"いぶりがっこ",
        "イブリガッコ":"いぶりがっこ"
    },
    "果実類":{
        "アボカド":"アボカド",
        "あぼかど":"アボカド",
        "アンズ":"あんず",
        "あんず":"あんず",
        "杏":"あんず",
        "イチゴ":"いちご",
        "いちご":"いちご",
        "苺":"いちご",
        "いちじく":"いちじく",
        "イチジク":"いちじく",
        "うめ":"うめ",
        "ウメ":"うめ",
        "梅":"うめ",
        "うめぼし":"うめぼし",
        "ウメボシ":"うめぼし",
        "梅干":"うめぼし",
        "みかん":"みかん",
        "ミカン":"みかん",
        "蜜柑":"みかん",
        "みかんじゅーす":"みかんジュース",
        "ミカンジュース":"みかんジュース",
        "みかんジュース":"みかんジュース",
        "蜜柑ジュース":"みかんジュース",
        "みかん　缶詰":"みかん　缶詰",
        "ミカン　缶詰":"みかん　缶詰",
        "みかん　かんづめ":"みかん　缶詰",
        "オリーブ":"オリーブ",
        "おりーぶ":"オリーブ",
        "マーマレード":"マーマレード",
        "まーまれーど":"マーマレード",
        "かき":"柿",
        "カキ":"柿",
        "柿":"柿",
        "かぼす":"かぼす",
        "カボス":"かぼす",
        "キウイフルーツ":"キウイフルーツ",
        "きういふるーつ":"キウイフルーツ",
        "グレープフルーツ":"グレープフルーツ",
        "ぐれーぷふるーつ":"グレープフルーツ",
        "すいか":"すいか",
        "スイカ":"すいか",
        "西瓜":"すいか",
        "すだち":"すだち",
        "スダチ":"すだち",
        "酢橘":"すだち",
        "ぷるーん":"プルーン",
        "プルーン":"プルーン",
        "なし":"なし",
        "ナシ":"なし",
        "梨":"なし",
        "パインアップル":"パインアップル",
        "パイナップル":"パインアップル",
        "ぱいなっぷる":"パインアップル",
        "ぱいんあっぷる":"パインアップル",
        "ぱいんあっぷる　缶詰":"パインアップル　缶詰",
        "パインアップル　缶詰":"パインアップル　缶詰",
        "パイナップル　缶詰":"パインアップル　缶詰",
        "はっさく":"はっさく",
        "八朔":"はっさく",
        "バナナ":"バナナ",
        "ばなな":"バナナ",
        "ぶどう":"ぶどう",
        "葡萄":"ぶどう",
        "ブドウ":"ぶどう",
        "ブルーベリー":"ブルーベリー",
        "ぶるーべりー":"ブルーベリー",
        "ブルーベリー　ジャム":"ブルーベリー　ジャム",
        "マンゴー":"マンゴー",
        "まんごー":"マンゴー",
        "ゆず":"ゆず",
        "柚子":"ゆず",
        "ユズ":"ゆず",
        "らいむ":"ライム",
        "ライム":"ライム",
        "れもん":"レモン",
        "レモン":"レモン",
        "もも　かんづめ":"もも　缶詰",
        "桃　缶詰":"もも　缶詰",
        "りんご":"りんご",
        "リンゴ":"りんご",
        "林檎":"りんご",
        "くこ":"くこ"
    },
    "キノコ類":{
        "えのきたけ":"えのきたけ",
        "榎茸":"えのきたけ",
        "えのきたけ　瓶詰":"えのきたけ　瓶詰",
        "榎茸　瓶詰":"えのきたけ　瓶詰",
        "きくらげ":"きくらげ",
        "キクラゲ":"きくらげ",
        "木耳":"きくらげ",
        "しろきくらげ":"しろきくらげ",
        "白木耳":"しろきくらげ",
        "シロキクラゲ":"しろきくらげ",
        "しいたけ":"しいたけ",
        "シイタケ":"しいたけ",
        "椎茸":"しいたけ",
        "ぶなしめじ":"ぶなしめじ",
        "ブナシメジ":"ぶなしめじ",
        "ほんしめじ":"ほんしめじ",
        "本しめじ":"ほんしめじ",
        "なめこ":"なめこ",
        "なめこ　缶詰":"なめこ　缶詰",
        "えりんぎ":"エリンギ",
        "エリンギ":"エリンギ",
        "まいたけ":"まいたけ",
        "舞茸":"まいたけ",
        "マイタケ":"まいたけ",
        "マッシュルーム":"マッシュルーム",
        "まっしゅるーむ":"マッシュルーム",
        "マッシュルーム　缶詰":"マッシュルーム　缶詰",
        "まっしゅるーむ　缶詰":"マッシュルーム　缶詰",
        "まつたけ":"まつたけ",
        "松茸":"まつたけ"
    },
    "藻類":{
        "のり":"のり",
        "ノリ":"のり",
        "海苔":"のり",
        "焼きのり":"焼きのり",
        "やきのり":"焼きのり",
        "刻み昆布":"刻み昆布",
        "きざみこんぶ":"刻み昆布",
        "けずりこんぶ":"削り昆布",
        "削り昆布":"削り昆布",
        "塩昆布":"塩昆布",
        "しおこんぶ":"塩昆布",
        "角寒天":"角寒天",
        "かくかんてん":"角寒天",
        "つくだに":"佃煮",
        "佃煮":"佃煮",
        "つくだ煮":"佃煮",
        "もずく":"もずく",
        "海蘊":"もずく",
        "わかめ":"わかめ",
        "ワカメ":"わかめ",
        "和布":"わかめ",
        "めかぶわかめ":"めかぶわかめ",
        "雌株和布":"めかぶわかめ",
        "粉寒天":"粉寒天",
        "コナカンテン":"粉寒天",
        "こなかんてん":"粉寒天",
        "ひじき":"ひじき",
        "ヒジキ":"ひじき"
    },
    "魚介類":{
        "あじ":"あじ",
        "鯵":"あじ",
        "あなご":"あなご",
        "穴子":"あなご",
        "あゆ":"あゆ",
        "鮎":"あゆ",
        "あんこう":"あんこう",
        "アンコウ":"あんこう",
        "鮟鱇":"あんこう",
        "あんこう　肝":"あんこう　肝",
        "アンコウ　肝":"あんこう　肝",
        "鮟鱇　肝":"あんこう　肝",
        "あんきも":"あんこう　肝",
        "いとよりだい":"いとよりだい",
        "片口鰯":"かたくちいわし",
        "かたくちいわし":"かたくちいわし",
        "カタクチイワシ":"かたくちいわし",
        "かたくちいわし　田作り":"かたくちいわし　田作り",
        "カタクチイワシ　田作り":"かたくちいわし　田作り",
        "かたくちいわし　たづくり":"かたくちいわし　田作り",
        "片口鰯　田作り":"かたくちいわし　田作り",
        "まいわし":"まいわし",
        "真鰯":"まいわし",
        "しらす":"しらす",
        "白州":"しらす",
        "シラス":"しらす",
        "いわし　缶詰":"いわし　缶詰",
        "イワシ　缶詰":"いわし　缶詰",
        "鰯　缶詰":"いわし　缶詰",
        "うなぎ":"うなぎ",
        "ウナギ":"うなぎ",
        "鰻":"うなぎ",
        "めかじき":"めかじき",
        "メカジキ":"めかじき",
        "かつお":"かつお",
        "カツオ":"かつお",
        "鰹":"かつお",
        "鰹節":"かつお節",
        "かつおぶし":"かつお節",
        "かつお節":"かつお節",
        "まがれい":"まがれい",
        "マガレイ":"まがれい",
        "きす":"きす",
        "キス":"きす",
        "鱚":"きす",
        "きちじ":"きちじ",
        "キチジ":"きちじ",
        "ぎんだら":"ぎんだら",
        "銀鱈":"ぎんだら",
        "ギンダラ":"ぎんだら",
        "きんめだい":"きんめだい",
        "金目鯛":"きんめだい",
        "キンメダイ":"きんめだい",
        "さけ":"さけ",
        "サケ":"さけ",
        "鮭":"さけ",
        "いくら":"いくら",
        "イクラ":"いくら",
        "しろさけ　水煮缶詰":"しろさけ　水煮缶詰",
        "白鮭　水煮缶詰":"しろさけ　水煮缶詰",
        "さば":"さば",
        "鯖":"さば",
        "さば　缶詰":"さば　缶詰",
        "鯖　缶詰":"さば　缶詰",
        "さめ":"さめ",
        "サメ":"さめ",
        "鮫":"さめ",
        "さわら":"さわら",
        "鰆":"さわら",
        "さんま":"さんま",
        "サンマ":"さんま",
        "秋刀魚":"さんま",
        "さんま　缶詰":"さんま　缶詰",
        "秋刀魚　缶詰":"さんま　缶詰",
        "ししゃも":"ししゃも",
        "シシャモ":"ししゃも",
        "柳葉魚":"ししゃも",
        "したびらめ":"したびらめ",
        "シタビラメ":"したびらめ",
        "舌鮃":"したびらめ",
        "スズキ":"すずき",
        "鱸":"すずき",
        "すずき":"すずき",
        "たい":"たい",
        "鯛":"たい",
        "たちうお":"たちうお",
        "タチウオ":"たちうお",
        "太刀魚":"たちうお",
        "たらこ":"たらこ",
        "タラコ":"たらこ",
        "鱈子":"たらこ",
        "辛子明太子":"からしめんたいこ",
        "からしめんたいこ":"からしめんたいこ",
        "たら":"たら",
        "タラ":"たら",
        "鱈":"たら",
        "しらこ":"しらこ",
        "白子":"しらこ",
        "でんぶ":"でんぶ",
        "田麩":"でんぶ",
        "かずのこ":"かずのこ",
        "数の子":"かずのこ",
        "カズノコ":"かずのこ",
        "はたはた":"はたはた",
        "ハタハタ":"はたはた",
        "ぶり":"ぶり",
        "ブリ":"ぶり",
        "鰤":"ぶり",
        "はまち":"はまち",
        "ハマチ":"はまち",
        "ほっけ":"ほっけ",
        "ホッケ":"ほっけ",
        "𩸽":"ほっけ",
        "まぐろ":"まぐろ",
        "マグロ":"まぐろ",
        "鮪":"まぐろ",
        "まぐろ　缶詰":"まぐろ　缶詰",
        "マグロ　缶詰":"まぐろ　缶詰",
        "鮪　缶詰":"まぐろ　缶詰",
        "わかさぎ":"わかさぎ",
        "ワカサギ":"わかさぎ",
        "鰙":"わかさぎ",
        "あかがい":"あかがい",
        "赤貝":"あかがい",
        "あさり":"あさり",
        "アサリ":"あさり",
        "浅利":"あさり",
        "あさり　缶詰":"あさり　缶詰",
        "アサリ　缶詰":"あさり　缶詰",
        "浅利　缶詰":"あさり　缶詰",
        "牡蠣":"牡蠣",
        "しじみ":"しじみ",
        "シジミ":"しじみ",
        "はまぐり":"はまぐり",
        "蛤":"はまぐり",
        "ハマグリ":"はまぐり",
        "ほたてがい":"ほたてがい",
        "帆立貝":"ほたてがい",
        "ホタテ貝":"ほたてがい",
        "ほたてがい　缶詰":"ほたてがい　缶詰",
        "ホタテ貝　缶詰":"ほたてがい　缶詰",
        "帆立貝　缶詰":"ほたてがい　缶詰",
        "あまえび":"あまえび",
        "甘エビ":"あまえび",
        "甘海老":"あまえび",
        "くるまえび":"くるまえび",
        "車海老":"くるまえび",
        "クルマエビ":"くるまえび",
        "さくらえび":"さくらえび",
        "桜海老":"さくらえび",
        "サクラエビ":"さくらえび",
        "大正えび":"大正えび",
        "たいしょうえび":"大正えび",
        "しばえび":"しばえび",
        "シバエビ":"しばえび",
        "芝えび":"しばえび",
        "ブラックタイガー":"ブラックタイガー",
        "ぶらっくたいがー":"ブラックタイガー",
        "干しえび":"干しえび",
        "ホシエビ":"干しえび",
        "ほしえび":"干しえび",
        "がざみ":"がざみ",
        "毛蟹":"毛がに",
        "けがに":"毛がに",
        "毛がに":"毛がに",
        "かに　缶詰":"かに　缶詰",
        "蟹　缶詰":"かに　缶詰",
        "カニ　缶詰":"かに　缶詰",
        "いか":"いか",
        "イカ":"いか",
        "烏賊":"いか",
        "するめ":"するめ",
        "スルメ":"するめ",
        "塩辛":"塩辛",
        "しおから":"塩辛",
        "たこ":"たこ",
        "タコ":"たこ",
        "蛸":"たこ",
        "うに":"うに",
        "ウニ":"うに",
        "雲丹":"うに",
        "くらげ":"くらげ",
        "クラゲ":"くらげ",
        "海月":"くらげ",
        "かにかま":"かにかま",
        "カニカマ":"かにかま",
        "かまぼこ":"かまぼこ",
        "カマボコ":"かまぼこ",
        "蒲鉾":"かまぼこ",
        "ちくわ":"ちくわ",
        "竹輪":"ちくわ",
        "つみれ":"つみれ",
        "ツミレ":"つみれ",
        "なると":"なると",
        "鳴門":"なると",
        "はんぺん":"はんぺん",
        "ハンペン":"はんぺん",
        "半片":"はんぺん",
        "さつま揚げ":"さつま揚げ",
        "さつまあげ":"さつまあげ",
        "魚肉ソーセージ":"魚肉ソーセージ",
        "ぎょにくそーせーじ":"魚肉ソーセージ",
        "アンチョビ":"アンチョビ",
        "あんちょび":"アンチョビ",
        "にじます":"にじます",
        "虹鱒":"にじます"
    },
    "肉類":{
        "うし　かた":"うし　かた",
        "牛　肩":"うし　かた",
        "うし　肩ロース":"うし　肩ロース",
        "牛　肩ロース":"うし　肩ロース",
        "うし　かたロース":"うし　肩ロース",
        "うし　サーロイン":"うし　サーロイン",
        "牛　サーロイン":"うし　サーロイン",
        "うし　ばら":"うし　ばら",
        "牛　ばら":"うし　ばら",
        "うし　もも":"うし　もも",
        "牛　腿":"うし　もも",
        "うし　ランプ":"うし　ランプ",
        "牛　ランプ":"うし　ランプ",
        "うし　ひき肉":"うし　ひき肉",
        "牛　挽肉":"うし　ひき肉",
        "うし　肝臓":"うし　肝臓",
        "うし　かんぞう":"うし　肝臓",
        "牛　肝臓":"うし　肝臓",
        "うし　腱":"うし　腱",
        "牛　腱":"うし　腱",
        "コンビーフ缶詰":"コンビーフ缶詰",
        "こんびーふかんづめ":"コンビーフ缶詰",
        "うま":"うま",
        "馬":"うま",
        "ぶた　かた":"ぶた　かた",
        "豚　肩":"ぶた　かた",
        "ぶた　肩ロース":"ぶた　肩ロース",
        "ぶた　かたろーす":"ぶた　肩ロース",
        "豚　肩ロース":"ぶた　肩ロース",
        "ぶた　ロース":"ぶた　ロース",
        "豚　ロース":"ぶた　ロース",
        "ぶた　ばら":"ぶた　ばら",
        "豚　バラ":"ぶた　ばら",
        "ぶた　ひれ":"ぶた　ヒレ",
        "ぶた　ヒレ":"ぶた　ヒレ",
        "豚　ヒレ":"ぶた　ヒレ",
        "ぶた　ひき肉":"ぶた　ひき肉",
        "豚　挽肉":"ぶた　ひき肉",
        "ぶた　とんそく":"ぶた　豚足",
        "ぶた　豚足":"ぶた　豚足",
        "豚　豚足":"ぶた　豚足",
        "ぶた　ロースハム":"ぶた　ロースハム",
        "豚　ロースハム":"ぶた　ロースハム",
        "ぶた　生ハム":"ぶた　生ハム",
        "豚　生ハム":"豚　生ハム",
        "ぶた　ベーコン":"ぶた　ベーコン",
        "豚　ベーコン":"ぶた　ベーコン",
        "ぶた　ソーセージ":"ぶた　ソーセージ",
        "豚　ソーセージ":"ぶた　ソーセージ",
        "ぶた　焼き豚":"ぶた　焼き豚",
        "豚　焼き豚":"ぶた　焼き豚",
        "ぶた　やきぶた":"ぶた　焼き豚",
        "ぶた　ゼラチン":"ぶた　ゼラチン",
        "豚　ゼラチン":"ぶた　ゼラチン",
        "ひつじ　かた":"ひつじ　肩",
        "羊　肩":"ひつじ　肩",
        "かも":"かも",
        "鴨":"かも",
        "カモ":"かも",
        "にわとり　手羽":"にわとり　手羽",
        "にわとり　てば":"にわとり　手羽",
        "鶏　手羽":"にわとり　手羽",
        "にわとり　むね":"にわとり　むね",
        "にわとり　胸":"にわとり　むね",
        "鶏　胸":"にわとり　むね",
        "にわとり　もも":"にわとり　もも",
        "にわとり　腿":"にわとり　もも",
        "鶏　腿":"にわとり　もも",
        "にわとり　ささみ":"にわとり　ささみ",
        "にわとり　笹身":"にわとり　ささみ",
        "鶏　笹身":"にわとり　ささみ",
        "にわとり　ひき肉":"にわとり　ひき肉",
        "にわとり　挽肉":"にわとり　ひき肉",
        "鶏　挽肉":"にわとり　ひき肉",
        "にわとり　かんぞう":"にわとり　肝臓",
        "にわとり　肝臓":"にわとり　肝臓",
        "鶏　肝臓":"にわとり　肝臓",
        "にわとり　すなぎも":"にわとり　すなぎも",
        "にわとり　砂肝":"にわとり　すなぎも",
        "鶏　砂肝":"にわとり　すなぎも",
        "にわとり　皮":"にわとり　皮",
        "にわとり　かわ":"にわとり　皮",
        "鶏　皮":"にわとり　皮",
        "にわとり　なんこつ":"にわとり　なんこつ",
        "にわとり　軟骨":"にわとり　なんこつ",
        "鶏　軟骨":"にわとり　なんこつ",
        "ぶた　焼き":"ぶた　焼き",
        "豚　焼き":"ぶた　焼き",
        "ぶた　やき":"ぶた　焼き",
        "にわとり　つくね":"にわとり　つくね",
        "にわとり　捏":"にわとり　つくね",
        "鶏　捏":"にわとり　つくね"
    },
    "鶏卵":{
        "うずら卵":"うずら卵",
        "うずらたまご":"うずら卵",
        "鶉卵":"うずら卵",
        "うずら卵　缶詰":"うずら卵　缶詰",
        "うずらたまご　缶詰":"うずら卵　缶詰",
        "鶉卵　缶詰":"うずら卵　缶詰",
        "鶏卵":"鶏卵",
        "けいらん":"鶏卵",
        "卵黄":"卵黄",
        "らんおう":"卵黄",
        "らんぱく":"卵白",
        "卵白":"卵白",
        "卵豆腐":"たまご豆腐",
        "たまごどうふ":"たまご豆腐",
        "玉子豆腐":"たまご豆腐",
        "卵焼き":"たまご焼き",
        "たまご焼き":"たまご焼き",
        "たまごやき":"たまご焼き",
        "皮蛋":"ピータン",
        "ぴーたん":"ピータン",
        "ピータン":"ピータン"
    },
    "乳類":{
        "ぎゅうにゅう":"牛乳",
        "牛乳":"牛乳",
        "ギュウニュウ":"牛乳",
        "脱脂粉乳":"脱脂粉乳",
        "だっしふんにゅう":"脱脂粉乳",
        "れんにゅう":"れんにゅう",
        "レンニュウ":"れんにゅう",
        "練乳":"れんにゅう",
        "クリーム":"クリーム",
        "くりーむ":"クリーム",
        "コーヒーホワイトナー":"コーヒーホワイトナー",
        "こーひーほわいとなー":"コーヒーホワイトナー",
        "ヨーグルト":"ヨーグルト",
        "よーぐると":"ヨーグルト",
        "乳酸菌飲料":"乳酸菌飲料",
        "ニュウサンキンインリョウ":"乳酸菌飲料",
        "にゅうさんきんいんりょう":"乳酸菌飲料",
        "カマンベール":"カマンベール",
        "かまんべーる":"カマンベール",
        "クリームチーズ":"クリームチーズ",
        "くりーむちーず":"クリームチーズ",
        "ブルーチーズ":"ブルーチーズ",
        "ぶるーちーず":"ブルーチーズ",
        "ぷろせすちーず":"プロセスチーズ",
        "プロセスチーズ":"プロセスチーズ",
        "モッツァレラ":"モッツァレラ",
        "もっつぁれら":"モッツァレラ"
    },
    "菓子類":{
        "ぱい":"パイ",
        "パイ":"パイ",
        "クラッカー":"クラッカー",
        "くらっかー":"クラッカー",
        "ポテトチップス":"ポテトチップス",
        "ぽてとちっぷす":"ポテトチップス",
        "ミルクチョコレート":"ミルクチョコレート",
        "みるくちょこれーと":"ミルクチョコレート"
    },
    "し好飲料":{
        "びーる":"ビール",
        "ビール":"ビール",
        "葡萄酒":"ぶどう酒",
        "ぶどう酒":"ぶどう酒",
        "ぶどうしゅ":"ぶどう酒",
        "紹興酒":"紹興酒",
        "しょうこうしゅ":"紹興酒",
        "梅酒":"梅酒",
        "ウメシュ":"梅酒",
        "うめしゅ":"梅酒",
        "ワイン":"ワイン",
        "わいん":"ワイン",
        "センチャ":"せん茶",
        "せん茶":"せん茶",
        "ほうじちゃ":"ほうじ茶",
        "ほうじ茶":"ほうじ茶",
        "こーひー":"コーヒー",
        "コーヒー":"コーヒー",
        "ここあ":"ココア",
        "ココア":"ココア",
        "アマザケ":"甘酒",
        "あまざけ":"甘酒"
    },
    "調味料及び香辛料":{
        "トマトピューレー":"トマトピューレー",
        "とまとぴゅーれー":"トマトピューレー",
        "トマトペースト":"トマトペースト",
        "とまとぺーすと":"トマトペースト",
        "とまとそーす":"トマトソース",
        "トマトソース":"トマトソース",
        "カレールウ":"カレールウ",
        "かれーるう":"カレールウ",
        "酒かす":"酒かす",
        "さけかす":"酒かす",
        "こうぼ":"酵母",
        "酵母":"酵母",
        "デミグラスソース":"デミグラスソース"
    }
}